{"email": "pujiermanto@gmail.com", "app_usage_time": {"Enter Email": 5, "Activity Usage | PM Tokoweb": 7, "Task Switching": 4, "CI4 di XAMPP \u2014 Mozilla Firefox": 5, "mouse-keybord-logger.py - python-project - Visual Studio Code": 12, "http://localhost:9091/api/send-activity - MindSparks - Dev Team": 1, "MINGW64:/c/Users/Laptop Store 95": 4, "MINGW64:/c/Users/Laptop Store 95/puji-project": 3, "MINGW64:/c/Users/Laptop Store 95/puji-project/python-project": 3}, "keyboard_usage": 0.00035011574074074074, "mouse_usage": 0.0, "created_at": "2025-01-14 16:16:11.195114"}